spacestills/__init__.py
spacestills/gui.py
spacestills-0.2.0.dist-info/LICENSE
spacestills-0.2.0.dist-info/METADATA
spacestills-0.2.0.dist-info/WHEEL
spacestills-0.2.0.dist-info/entry_points.txt
spacestills-0.2.0.dist-info/top_level.txt
spacestills-0.2.0.dist-info/RECORD
