Metadata-Version: 2.1
Name: spacestills
Version: 0.2.0
Summary: NASA TV still frame viewer
Home-page: https://github.com/pamoroso/spacestills
Author: Paolo Amoroso
Author-email: info@paoloamoroso.com
License: MIT
Platform: UNKNOWN
Classifier: Development Status :: 5 - Production/Stable
Classifier: License :: OSI Approved :: MIT License
Classifier: Programming Language :: Python :: 3
Classifier: Programming Language :: Python :: 3.6
Classifier: Operating System :: OS Independent
Classifier: Topic :: Scientific/Engineering
Requires-Python: >=3.6
Requires-Dist: pysimplegui
Requires-Dist: pillow
Requires-Dist: requests
